nugit/DESC.md
nugit/__init__.py
nugit/actions.py
nugit/argsparser.py
nugit/constants.py
nugit/exeptions.py
nugit/jobs.py
nugit/entrypoints/__init__.py
nugit/templates/base
nugit/templates/cfg.yaml
nugit-1.1.0.dist-info/LICENSE
nugit-1.1.0.dist-info/METADATA
nugit-1.1.0.dist-info/WHEEL
nugit-1.1.0.dist-info/entry_points.txt
nugit-1.1.0.dist-info/top_level.txt
nugit-1.1.0.dist-info/RECORD
