Metadata-Version: 2.1
Name: nugit
Version: 1.1.0
Summary: A git-hooks tool that works according to the script described in the yaml configuration file.
Author-email: Lev Zlobin <lengthylyova@gmail.com>
License: MIT License
Project-URL: Homepage, https://github.com/lengthylyova/nugit
Project-URL: Issues, https://github.com/lengthylyova/nugit/issues
Keywords: python,git,hook,git-hooks
Classifier: Programming Language :: Python
License-File: LICENSE
Requires-Dist: PyYAML >=6.0.2
Requires-Dist: Jinja2 >=3.1.4
Provides-Extra: dev
Requires-Dist: nugit >=1.0.2 ; extra == 'dev'
Requires-Dist: flake8 >=7.1.1 ; extra == 'dev'
